[
	{
		"question": "Выберите истинный исторический факт.",
		"answerTrue": "Бумеранг был изобретен в Австралии 15 тыс. лет до н.э.",
		"answerFalse": "Бумеранг изобрели в 10 веке во Франции.",
		"info": "15 тыс. лет до н.э. — Бумеранг в Австралии"
	},
	{
		"question": "Выберите истинный исторический факт.",
		"answerTrue": "Первая фанера была создана в Древнем Египте.",
		"answerFalse": "Первая фанера была создана в Древней Греции.",
		"info": "3500 г. до н. э.: Фанера в Древнем Египте."
	},
	{
		"question": "Выберите истинный исторический факт.",
		"answerTrue": "Стекло было изобретено в Древнем Египте во 2-м веке до н.э.",
		"answerFalse": "Стекло было изобретено в 1 веке до н.э. в Древнем Риме.",
		"info": "2-е тысячелетие до н.э. Стекло в Древнем Египте."
	},
	{
		"question": "Выберите истинный исторический факт.",
		"answerTrue": "Прототип паровой турбины был создан Героном Александрийским в 1 веке.",
		"answerFalse": "Прототип паровой турбины создали группа ученых в 10 веке.",
		"info": "1 век: Прототип паровой турбины: Герон Александрийский."
	},
	{
		"question": "Выберите истинный исторический факт.",
		"answerTrue": "Первый в мире огнемет был изобретен в Китае.",
		"answerFalse": "Первый в мире огнемет изобрели в нацисткой Германии.",
		"info": "1132: Китайскими оружейниками был изобретён первый в мире огнемёт."
	},
	{
		"question": "Выберите истинный исторический факт.",
		"answerTrue": "Леонардо да Винчи создал современные ножницы.",
		"answerFalse": "Современные ножницы создал физик Никола Тесла.",
		"info": "1500: Современные ножницы: Леонардо да Винчи."
	},
	{
		"question": "Выберите истинный исторический факт.",
		"answerTrue": "Паровая турбина Джованни Бранка была создана в 1869 году.",
		"answerFalse": "Реактивная турбина Джованни Бранка была создана в 1869 году.",
		"info": "1629: Паровая турбина: Джованни Бранка."
	},
	{
		"question": "Выберите истинный исторический факт.",
		"answerTrue": "В 1775 г. англичанин Джон Утрэм изобретает трамвай на конной тяге.",
		"answerFalse": "В 1875 г. американец Джон Утрэм изобретает трамвай на электрической тяге.",
		"info": "1775: Англичанин Джон Утрэм изобретает трамвай на конной тяге - конку."
	},
	{
		"question": "Выберите истинный исторический факт.",
		"answerTrue": "Современный велосипед с педалями и седлом создали в 1839 г.",
		"answerFalse": "В 1910 г. был создан создан современный велосипед.",
		"info": "1839: Современный велосипед с педалями и седлом: Киркпатрик Макмиллан."
	},
	{
		"question": "Выберите истинный исторический факт.",
		"answerTrue": "LEGO создало свои пластмассовые кубики в 1949 г..",
		"answerFalse": "Первое LEGO появилось в 1987 году.",
		"info": "1949: Пластмассовые кубики LEGO."
	}
]